{
  "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": {
    "reset_time": 1746369986.929308,
    "remaining": 5000,
    "backoff_until": 0,
    "consecutive_errors": 0
  },
  "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": {
    "reset_time": 1746369986.929308,
    "remaining": 5000,
    "backoff_until": 0,
    "consecutive_errors": 0
  },
  "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": {
    "reset_time": 1746369986.929308,
    "remaining": 5000,
    "backoff_until": 0,
    "consecutive_errors": 0
  },
  "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": {
    "reset_time": 1746369986.929308,
    "remaining": 5000,
    "backoff_until": 0,
    "consecutive_errors": 0
  },
  "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": {
    "reset_time": 1746369986.929308,
    "remaining": 5000,
    "backoff_until": 0,
    "consecutive_errors": 0
  },
  "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": {
    "reset_time": 1746369986.929308,
    "remaining": 5000,
    "backoff_until": 0,
    "consecutive_errors": 0
  },
  "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": {
    "reset_time": 1746369986.929308,
    "remaining": 5000,
    "backoff_until": 0,
    "consecutive_errors": 0
  },
  "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": {
    "reset_time": 1746369986.929308,
    "remaining": 5000,
    "backoff_until": 0,
    "consecutive_errors": 0
  },
  "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": {
    "reset_time": 1746369986.929308,
    "remaining": 5000,
    "backoff_until": 0,
    "consecutive_errors": 0
  },
  "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": {
    "reset_time": 1746369986.929308,
    "remaining": 5000,
    "backoff_until": 0,
    "consecutive_errors": 0
  },
  "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": {
    "reset_time": 1746369986.929308,
    "remaining": 5000,
    "backoff_until": 0,
    "consecutive_errors": 0
  },
  "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": {
    "reset_time": 1746369986.929308,
    "remaining": 5000,
    "backoff_until": 0,
    "consecutive_errors": 0
  },
  "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": {
    "reset_time": 1746369986.929308,
    "remaining": 5000,
    "backoff_until": 0,
    "consecutive_errors": 0
  },
  "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": {
    "reset_time": 1746369986.929308,
    "remaining": 5000,
    "backoff_until": 0,
    "consecutive_errors": 0
  },
  "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": {
    "reset_time": 1746369986.929308,
    "remaining": 5000,
    "backoff_until": 0,
    "consecutive_errors": 0
  }
}